annict/__init__.py
annict/api.py
annict/auth.py
annict/cursors.py
annict/models.py
annict/parsers.py
annict/services.py
annict/utils.py
annict-0.7.0.dist-info/LICENSE
annict-0.7.0.dist-info/WHEEL
annict-0.7.0.dist-info/METADATA
annict-0.7.0.dist-info/RECORD
